liulianmao/__init__.py
liulianmao/__main__.py
liulianmao/client/__init__.py
liulianmao/client/agent/__init__.py
liulianmao/client/agent/agent_judge.py
liulianmao/client/api/__init__.py
liulianmao/client/api/liulianmao.py
liulianmao/client/api/llama.py
liulianmao/client/api/openai.py
liulianmao/client/api/README.md
liulianmao/client/api/zhipu.py
liulianmao/client/core.py
liulianmao/client/langchain.py
liulianmao/client/sdk/openai.py
liulianmao/client/sdk/zhipu.py
liulianmao/client/utils/__init__.py
liulianmao/client/utils/file.py
liulianmao/client/utils/geo.py
liulianmao/client/utils/search.py
liulianmao/client/utils/traffic_jam.py
liulianmao/client/utils/weather.py
liulianmao/client/utils/website.py
liulianmao/const.py
liulianmao/module/__init__.py
liulianmao/module/authentication.py
liulianmao/module/config.py
liulianmao/module/const.py
liulianmao/module/log.py
liulianmao/module/model.py
liulianmao/module/runtime.py
liulianmao/module/storage.py
liulianmao/module/sync.py
liulianmao/tool/__init__.py
liulianmao/tool/continuous_chat.py
liulianmao/tool/translator_gui.py
liulianmao/tool/tts.py
liulianmao-2.4.0.dist-info/LICENSE
liulianmao-2.4.0.dist-info/METADATA
liulianmao-2.4.0.dist-info/WHEEL
liulianmao-2.4.0.dist-info/RECORD
