Metadata-Version: 2.1
Name: liulianmao
Version: 2.4.0
Summary: A LLM client for use from the command line or IDE.
Home-page: https://github.com/LaoshuBaby/liulianmao
License: MIT
Author: 快乐的老鼠宝宝
Author-email: laoshubaby@protonmail.com
Requires-Python: >=3.11,<4.0
Classifier: License :: OSI Approved :: MIT License
Classifier: Operating System :: OS Independent
Classifier: Programming Language :: Python :: 3
Classifier: Programming Language :: Python :: 3.11
Classifier: Programming Language :: Python :: 3.12
Classifier: Programming Language :: Python :: 3.13
Provides-Extra: langchain-support
Requires-Dist: hellologger
Requires-Dist: loguru (>=0.5.3)
Requires-Dist: requests (>=2.26.0)
Project-URL: Repository, https://github.com/LaoshuBaby/liulianmao
